validat/__init__.py
validat/exceptions/__init__.py
validat/exceptions/base.py
validat/validators/__init__.py
validat/validators/email.py
validat/validators/phone.py
validat/validators/url.py
validat-0.0.7.dist-info/licenses/LICENSE
validat-0.0.7.dist-info/METADATA
validat-0.0.7.dist-info/WHEEL
validat-0.0.7.dist-info/top_level.txt
validat-0.0.7.dist-info/RECORD
